mflt_compact_log/__init__.py
mflt_compact_log/compact.py
mflt_compact_log/log_fmt.py
mflt_compact_log/printf.py
mflt_compact_log/py.typed
mflt_compact_log-0.1.1.dist-info/LICENSE
mflt_compact_log-0.1.1.dist-info/METADATA
mflt_compact_log-0.1.1.dist-info/WHEEL
mflt_compact_log-0.1.1.dist-info/entry_points.txt
mflt_compact_log-0.1.1.dist-info/top_level.txt
mflt_compact_log-0.1.1.dist-info/RECORD
