Metadata-Version: 2.2
Name: mflt-compact-log
Version: 0.1.1
Author-email: Memfault <hello@memfault.com>
License: Copyright (c) 2019 - Present, Memfault
Requires-Python: <4.0,>=3.8
License-File: LICENSE
Requires-Dist: cbor2<6,>=5
Requires-Dist: click<9.0,>=8.0
Requires-Dist: prettytable<4,>=3
Requires-Dist: pyelftools<0.32,>=0.31
Requires-Dist: pyparsing<4,>=3.1.4
Requires-Dist: typing_extensions<5,>=4.12.2
